halloumi_cloudwatch_dashboard/__init__.py
halloumi_cloudwatch_dashboard/py.typed
halloumi_cloudwatch_dashboard/_jsii/__init__.py
halloumi_cloudwatch_dashboard/_jsii/halloumi-cloudwatch-dashboard@2.0.0.jsii.tgz
halloumi_cloudwatch_dashboard-2.0.0.dist-info/LICENSE
halloumi_cloudwatch_dashboard-2.0.0.dist-info/METADATA
halloumi_cloudwatch_dashboard-2.0.0.dist-info/WHEEL
halloumi_cloudwatch_dashboard-2.0.0.dist-info/top_level.txt
halloumi_cloudwatch_dashboard-2.0.0.dist-info/RECORD
